<?xml version="1.0" encoding="UTF-8"?>
<GenRun Id="synth_1" LaunchPart="xc7z020clg400-1" LaunchTime="1522102960">
  <File Type="VDS-TIMING-PB" Name="vcnnbd_wrapper_timing_summary_synth.pb"/>
  <File Type="VDS-TIMINGSUMMARY" Name="vcnnbd_wrapper_timing_summary_synth.rpt"/>
  <File Type="RDS-DCP" Name="vcnnbd_wrapper.dcp"/>
  <File Type="RDS-UTIL-PB" Name="vcnnbd_wrapper_utilization_synth.pb"/>
  <File Type="RDS-UTIL" Name="vcnnbd_wrapper_utilization_synth.rpt"/>
  <File Type="RDS-PROPCONSTRS" Name="vcnnbd_wrapper_drc_synth.rpt"/>
  <File Type="RDS-RDS" Name="vcnnbd_wrapper.vds"/>
  <File Type="PA-TCL" Name="vcnnbd_wrapper.tcl"/>
  <FileSet Name="sources" Type="DesignSrcs" RelSrcDir="$PSRCDIR/sources_1">
    <Filter Type="Srcs"/>
    <File Path="$PSRCDIR/sources_1/bd/vcnnbd/vcnnbd.bd">
      <FileInfo>
        <Attr Name="UsedIn" Val="synthesis"/>
        <Attr Name="UsedIn" Val="implementation"/>
        <Attr Name="UsedIn" Val="simulation"/>
      </FileInfo>
    </File>
    <File Path="$PSRCDIR/sources_1/bd/vcnnbd/hdl/vcnnbd_wrapper.v">
      <FileInfo>
        <Attr Name="UsedIn" Val="synthesis"/>
        <Attr Name="UsedIn" Val="implementation"/>
        <Attr Name="UsedIn" Val="simulation"/>
      </FileInfo>
    </File>
    <File Path="$PSRCDIR/sources_1/bd/vcnnbd/ip/vcnnbd_blk_mem_gen_0_0/input_bram.coe">
      <FileInfo>
        <Attr Name="UsedIn" Val="synthesis"/>
        <Attr Name="UsedIn" Val="simulation"/>
      </FileInfo>
    </File>
    <File Path="$PSRCDIR/sources_1/bd/vcnnbd/ip/vcnnbd_blk_mem_gen_0_1/weight_bram.coe">
      <FileInfo>
        <Attr Name="UsedIn" Val="synthesis"/>
        <Attr Name="UsedIn" Val="simulation"/>
      </FileInfo>
    </File>
    <File Path="$PSRCDIR/sources_1/bd/vcnnbd/ip/conv2_weights.coe">
      <FileInfo>
        <Attr Name="UsedIn" Val="synthesis"/>
        <Attr Name="UsedIn" Val="simulation"/>
      </FileInfo>
    </File>
    <Config>
      <Option Name="DesignMode" Val="RTL"/>
      <Option Name="TopModule" Val="vcnnbd_wrapper"/>
    </Config>
  </FileSet>
  <FileSet Name="constrs_in" Type="Constrs" RelSrcDir="$PSRCDIR/constrs_1">
    <Filter Type="Constrs"/>
    <File Path="$PSRCDIR/constrs_1/new/vcnnbd_wrapper.xdc">
      <FileInfo>
        <Attr Name="UsedIn" Val="synthesis"/>
        <Attr Name="UsedIn" Val="implementation"/>
      </FileInfo>
    </File>
    <Config>
      <Option Name="TargetConstrsFile" Val="$PSRCDIR/constrs_1/new/vcnnbd_wrapper.xdc"/>
      <Option Name="ConstrsType" Val="XDC"/>
    </Config>
  </FileSet>
  <Strategy Version="1" Minor="2">
    <StratHandle Name="Vivado Synthesis Defaults" Flow="Vivado Synthesis 2017"/>
    <Step Id="synth_design"/>
  </Strategy>
  <BlockFileSet Type="BlockSrcs" Name="vcnnbd_blk_mem_gen_0_1"/>
  <BlockFileSet Type="BlockSrcs" Name="vcnnbd_output_bram_mem_0"/>
  <BlockFileSet Type="BlockSrcs" Name="vcnnbd_axi_smc_0"/>
  <BlockFileSet Type="BlockSrcs" Name="vcnnbd_conv1l_top_0_1"/>
  <BlockFileSet Type="BlockSrcs" Name="vcnnbd_conv1l_top_0_0"/>
</GenRun>
